<?xml version="1.0" encoding="UTF-8"?>
<con:soapui-project id="f01bd2a5-60a6-48d4-9c12-f31c0988fed6" activeEnvironment="Default" name="airport" resourceRoot="" soapui-version="5.3.0" abortOnError="false" runType="SEQUENTIAL" xmlns:con="http://eviware.com/soapui/config"><con:settings/><con:interface xsi:type="con:WsdlInterface" id="e9a733aa-c4b8-419f-a7bc-503c15874b0c" wsaVersion="NONE" name="airportSoap" type="wsdl" bindingName="{http://www.webserviceX.NET}airportSoap" soapVersion="1_1" anonymous="optional" definition="http://www.webservicex.net/airport.asmx?WSDL" xmlns:xsi="http://www.w3.org/2001/XMLSchema-instance"><con:settings/><con:definitionCache type="TEXT" rootPart="http://www.webservicex.net/airport.asmx?WSDL"><con:part><con:url>http://www.webservicex.net/airport.asmx?WSDL</con:url><con:content><![CDATA[<wsdl:definitions targetNamespace="http://www.webserviceX.NET" xmlns:tm="http://microsoft.com/wsdl/mime/textMatching/" xmlns:soapenc="http://schemas.xmlsoap.org/soap/encoding/" xmlns:mime="http://schemas.xmlsoap.org/wsdl/mime/" xmlns:tns="http://www.webserviceX.NET" xmlns:soap="http://schemas.xmlsoap.org/wsdl/soap/" xmlns:s="http://www.w3.org/2001/XMLSchema" xmlns:soap12="http://schemas.xmlsoap.org/wsdl/soap12/" xmlns:http="http://schemas.xmlsoap.org/wsdl/http/" xmlns:wsdl="http://schemas.xmlsoap.org/wsdl/">
  <wsdl:types>
    <s:schema elementFormDefault="qualified" targetNamespace="http://www.webserviceX.NET">
      <s:element name="getAirportInformationByISOCountryCode">
        <s:complexType>
          <s:sequence>
            <s:element minOccurs="0" maxOccurs="1" name="CountryAbbrviation" type="s:string"/>
          </s:sequence>
        </s:complexType>
      </s:element>
      <s:element name="getAirportInformationByISOCountryCodeResponse">
        <s:complexType>
          <s:sequence>
            <s:element minOccurs="0" maxOccurs="1" name="getAirportInformationByISOCountryCodeResult" type="s:string"/>
          </s:sequence>
        </s:complexType>
      </s:element>
      <s:element name="getAirportInformationByCityOrAirportName">
        <s:complexType>
          <s:sequence>
            <s:element minOccurs="0" maxOccurs="1" name="cityOrAirportName" type="s:string"/>
          </s:sequence>
        </s:complexType>
      </s:element>
      <s:element name="getAirportInformationByCityOrAirportNameResponse">
        <s:complexType>
          <s:sequence>
            <s:element minOccurs="0" maxOccurs="1" name="getAirportInformationByCityOrAirportNameResult" type="s:string"/>
          </s:sequence>
        </s:complexType>
      </s:element>
      <s:element name="GetAirportInformationByCountry">
        <s:complexType>
          <s:sequence>
            <s:element minOccurs="0" maxOccurs="1" name="country" type="s:string"/>
          </s:sequence>
        </s:complexType>
      </s:element>
      <s:element name="GetAirportInformationByCountryResponse">
        <s:complexType>
          <s:sequence>
            <s:element minOccurs="0" maxOccurs="1" name="GetAirportInformationByCountryResult" type="s:string"/>
          </s:sequence>
        </s:complexType>
      </s:element>
      <s:element name="getAirportInformationByAirportCode">
        <s:complexType>
          <s:sequence>
            <s:element minOccurs="0" maxOccurs="1" name="airportCode" type="s:string"/>
          </s:sequence>
        </s:complexType>
      </s:element>
      <s:element name="getAirportInformationByAirportCodeResponse">
        <s:complexType>
          <s:sequence>
            <s:element minOccurs="0" maxOccurs="1" name="getAirportInformationByAirportCodeResult" type="s:string"/>
          </s:sequence>
        </s:complexType>
      </s:element>
      <s:element name="string" nillable="true" type="s:string"/>
    </s:schema>
  </wsdl:types>
  <wsdl:message name="getAirportInformationByISOCountryCodeSoapIn">
    <wsdl:part name="parameters" element="tns:getAirportInformationByISOCountryCode"/>
  </wsdl:message>
  <wsdl:message name="getAirportInformationByISOCountryCodeSoapOut">
    <wsdl:part name="parameters" element="tns:getAirportInformationByISOCountryCodeResponse"/>
  </wsdl:message>
  <wsdl:message name="getAirportInformationByCityOrAirportNameSoapIn">
    <wsdl:part name="parameters" element="tns:getAirportInformationByCityOrAirportName"/>
  </wsdl:message>
  <wsdl:message name="getAirportInformationByCityOrAirportNameSoapOut">
    <wsdl:part name="parameters" element="tns:getAirportInformationByCityOrAirportNameResponse"/>
  </wsdl:message>
  <wsdl:message name="GetAirportInformationByCountrySoapIn">
    <wsdl:part name="parameters" element="tns:GetAirportInformationByCountry"/>
  </wsdl:message>
  <wsdl:message name="GetAirportInformationByCountrySoapOut">
    <wsdl:part name="parameters" element="tns:GetAirportInformationByCountryResponse"/>
  </wsdl:message>
  <wsdl:message name="getAirportInformationByAirportCodeSoapIn">
    <wsdl:part name="parameters" element="tns:getAirportInformationByAirportCode"/>
  </wsdl:message>
  <wsdl:message name="getAirportInformationByAirportCodeSoapOut">
    <wsdl:part name="parameters" element="tns:getAirportInformationByAirportCodeResponse"/>
  </wsdl:message>
  <wsdl:message name="getAirportInformationByISOCountryCodeHttpGetIn">
    <wsdl:part name="CountryAbbrviation" type="s:string"/>
  </wsdl:message>
  <wsdl:message name="getAirportInformationByISOCountryCodeHttpGetOut">
    <wsdl:part name="Body" element="tns:string"/>
  </wsdl:message>
  <wsdl:message name="getAirportInformationByCityOrAirportNameHttpGetIn">
    <wsdl:part name="cityOrAirportName" type="s:string"/>
  </wsdl:message>
  <wsdl:message name="getAirportInformationByCityOrAirportNameHttpGetOut">
    <wsdl:part name="Body" element="tns:string"/>
  </wsdl:message>
  <wsdl:message name="GetAirportInformationByCountryHttpGetIn">
    <wsdl:part name="country" type="s:string"/>
  </wsdl:message>
  <wsdl:message name="GetAirportInformationByCountryHttpGetOut">
    <wsdl:part name="Body" element="tns:string"/>
  </wsdl:message>
  <wsdl:message name="getAirportInformationByAirportCodeHttpGetIn">
    <wsdl:part name="airportCode" type="s:string"/>
  </wsdl:message>
  <wsdl:message name="getAirportInformationByAirportCodeHttpGetOut">
    <wsdl:part name="Body" element="tns:string"/>
  </wsdl:message>
  <wsdl:message name="getAirportInformationByISOCountryCodeHttpPostIn">
    <wsdl:part name="CountryAbbrviation" type="s:string"/>
  </wsdl:message>
  <wsdl:message name="getAirportInformationByISOCountryCodeHttpPostOut">
    <wsdl:part name="Body" element="tns:string"/>
  </wsdl:message>
  <wsdl:message name="getAirportInformationByCityOrAirportNameHttpPostIn">
    <wsdl:part name="cityOrAirportName" type="s:string"/>
  </wsdl:message>
  <wsdl:message name="getAirportInformationByCityOrAirportNameHttpPostOut">
    <wsdl:part name="Body" element="tns:string"/>
  </wsdl:message>
  <wsdl:message name="GetAirportInformationByCountryHttpPostIn">
    <wsdl:part name="country" type="s:string"/>
  </wsdl:message>
  <wsdl:message name="GetAirportInformationByCountryHttpPostOut">
    <wsdl:part name="Body" element="tns:string"/>
  </wsdl:message>
  <wsdl:message name="getAirportInformationByAirportCodeHttpPostIn">
    <wsdl:part name="airportCode" type="s:string"/>
  </wsdl:message>
  <wsdl:message name="getAirportInformationByAirportCodeHttpPostOut">
    <wsdl:part name="Body" element="tns:string"/>
  </wsdl:message>
  <wsdl:portType name="airportSoap">
    <wsdl:operation name="getAirportInformationByISOCountryCode">
      <wsdl:documentation>Get Airport Code, CityOrAirport Name, Country, Country Abbrv, CountryCode,GMT Offset Runway Length in Feet, Runway Elevation in Feet,Latitude in Degree,Latitude in Minute Latitude in Second,Latitude in N/S, Longitude in Degree, Longitude in Minute, Longitude in Seconds and longitude E/W by ISO country code</wsdl:documentation>
      <wsdl:input message="tns:getAirportInformationByISOCountryCodeSoapIn"/>
      <wsdl:output message="tns:getAirportInformationByISOCountryCodeSoapOut"/>
    </wsdl:operation>
    <wsdl:operation name="getAirportInformationByCityOrAirportName">
      <wsdl:documentation>Get Airport Code, CityOrAirport Name, Country, Country Abbrv, CountryCode,GMT Offset Runway Length in Feet, Runway Elevation in Feet,Latitude in Degree,Latitude in Minute Latitude in Second,Latitude in N/S, Longitude in Degree, Longitude in Minute, Longitude in Seconds and longitude E/W by city or airport name</wsdl:documentation>
      <wsdl:input message="tns:getAirportInformationByCityOrAirportNameSoapIn"/>
      <wsdl:output message="tns:getAirportInformationByCityOrAirportNameSoapOut"/>
    </wsdl:operation>
    <wsdl:operation name="GetAirportInformationByCountry">
      <wsdl:documentation>Get Airport Code, CityOrAirport Name, Country, Country Abbrv, CountryCode,GMT Offset Runway Length in Feet, Runway Elevation in Feet,Latitude in Degree,Latitude in Minute Latitude in Second,Latitude in N/S, Longitude in Degree, Longitude in Minute, Longitude in Seconds and longitude E/W by country name</wsdl:documentation>
      <wsdl:input message="tns:GetAirportInformationByCountrySoapIn"/>
      <wsdl:output message="tns:GetAirportInformationByCountrySoapOut"/>
    </wsdl:operation>
    <wsdl:operation name="getAirportInformationByAirportCode">
      <wsdl:documentation>Get Airport Code, CityOrAirport Name, Country, Country Abbrv, CountryCode,GMT Offset Runway Length in Feet, Runway Elevation in Feet,Latitude in Degree,Latitude in Minute Latitude in Second,Latitude in N/S, Longitude in Degree, Longitude in Minute, Longitude in Seconds and longitude E/W by airport code</wsdl:documentation>
      <wsdl:input message="tns:getAirportInformationByAirportCodeSoapIn"/>
      <wsdl:output message="tns:getAirportInformationByAirportCodeSoapOut"/>
    </wsdl:operation>
  </wsdl:portType>
  <wsdl:portType name="airportHttpGet">
    <wsdl:operation name="getAirportInformationByISOCountryCode">
      <wsdl:documentation>Get Airport Code, CityOrAirport Name, Country, Country Abbrv, CountryCode,GMT Offset Runway Length in Feet, Runway Elevation in Feet,Latitude in Degree,Latitude in Minute Latitude in Second,Latitude in N/S, Longitude in Degree, Longitude in Minute, Longitude in Seconds and longitude E/W by ISO country code</wsdl:documentation>
      <wsdl:input message="tns:getAirportInformationByISOCountryCodeHttpGetIn"/>
      <wsdl:output message="tns:getAirportInformationByISOCountryCodeHttpGetOut"/>
    </wsdl:operation>
    <wsdl:operation name="getAirportInformationByCityOrAirportName">
      <wsdl:documentation>Get Airport Code, CityOrAirport Name, Country, Country Abbrv, CountryCode,GMT Offset Runway Length in Feet, Runway Elevation in Feet,Latitude in Degree,Latitude in Minute Latitude in Second,Latitude in N/S, Longitude in Degree, Longitude in Minute, Longitude in Seconds and longitude E/W by city or airport name</wsdl:documentation>
      <wsdl:input message="tns:getAirportInformationByCityOrAirportNameHttpGetIn"/>
      <wsdl:output message="tns:getAirportInformationByCityOrAirportNameHttpGetOut"/>
    </wsdl:operation>
    <wsdl:operation name="GetAirportInformationByCountry">
      <wsdl:documentation>Get Airport Code, CityOrAirport Name, Country, Country Abbrv, CountryCode,GMT Offset Runway Length in Feet, Runway Elevation in Feet,Latitude in Degree,Latitude in Minute Latitude in Second,Latitude in N/S, Longitude in Degree, Longitude in Minute, Longitude in Seconds and longitude E/W by country name</wsdl:documentation>
      <wsdl:input message="tns:GetAirportInformationByCountryHttpGetIn"/>
      <wsdl:output message="tns:GetAirportInformationByCountryHttpGetOut"/>
    </wsdl:operation>
    <wsdl:operation name="getAirportInformationByAirportCode">
      <wsdl:documentation>Get Airport Code, CityOrAirport Name, Country, Country Abbrv, CountryCode,GMT Offset Runway Length in Feet, Runway Elevation in Feet,Latitude in Degree,Latitude in Minute Latitude in Second,Latitude in N/S, Longitude in Degree, Longitude in Minute, Longitude in Seconds and longitude E/W by airport code</wsdl:documentation>
      <wsdl:input message="tns:getAirportInformationByAirportCodeHttpGetIn"/>
      <wsdl:output message="tns:getAirportInformationByAirportCodeHttpGetOut"/>
    </wsdl:operation>
  </wsdl:portType>
  <wsdl:portType name="airportHttpPost">
    <wsdl:operation name="getAirportInformationByISOCountryCode">
      <wsdl:documentation>Get Airport Code, CityOrAirport Name, Country, Country Abbrv, CountryCode,GMT Offset Runway Length in Feet, Runway Elevation in Feet,Latitude in Degree,Latitude in Minute Latitude in Second,Latitude in N/S, Longitude in Degree, Longitude in Minute, Longitude in Seconds and longitude E/W by ISO country code</wsdl:documentation>
      <wsdl:input message="tns:getAirportInformationByISOCountryCodeHttpPostIn"/>
      <wsdl:output message="tns:getAirportInformationByISOCountryCodeHttpPostOut"/>
    </wsdl:operation>
    <wsdl:operation name="getAirportInformationByCityOrAirportName">
      <wsdl:documentation>Get Airport Code, CityOrAirport Name, Country, Country Abbrv, CountryCode,GMT Offset Runway Length in Feet, Runway Elevation in Feet,Latitude in Degree,Latitude in Minute Latitude in Second,Latitude in N/S, Longitude in Degree, Longitude in Minute, Longitude in Seconds and longitude E/W by city or airport name</wsdl:documentation>
      <wsdl:input message="tns:getAirportInformationByCityOrAirportNameHttpPostIn"/>
      <wsdl:output message="tns:getAirportInformationByCityOrAirportNameHttpPostOut"/>
    </wsdl:operation>
    <wsdl:operation name="GetAirportInformationByCountry">
      <wsdl:documentation>Get Airport Code, CityOrAirport Name, Country, Country Abbrv, CountryCode,GMT Offset Runway Length in Feet, Runway Elevation in Feet,Latitude in Degree,Latitude in Minute Latitude in Second,Latitude in N/S, Longitude in Degree, Longitude in Minute, Longitude in Seconds and longitude E/W by country name</wsdl:documentation>
      <wsdl:input message="tns:GetAirportInformationByCountryHttpPostIn"/>
      <wsdl:output message="tns:GetAirportInformationByCountryHttpPostOut"/>
    </wsdl:operation>
    <wsdl:operation name="getAirportInformationByAirportCode">
      <wsdl:documentation>Get Airport Code, CityOrAirport Name, Country, Country Abbrv, CountryCode,GMT Offset Runway Length in Feet, Runway Elevation in Feet,Latitude in Degree,Latitude in Minute Latitude in Second,Latitude in N/S, Longitude in Degree, Longitude in Minute, Longitude in Seconds and longitude E/W by airport code</wsdl:documentation>
      <wsdl:input message="tns:getAirportInformationByAirportCodeHttpPostIn"/>
      <wsdl:output message="tns:getAirportInformationByAirportCodeHttpPostOut"/>
    </wsdl:operation>
  </wsdl:portType>
  <wsdl:binding name="airportSoap" type="tns:airportSoap">
    <soap:binding transport="http://schemas.xmlsoap.org/soap/http"/>
    <wsdl:operation name="getAirportInformationByISOCountryCode">
      <soap:operation soapAction="http://www.webserviceX.NET/getAirportInformationByISOCountryCode" style="document"/>
      <wsdl:input>
        <soap:body use="literal"/>
      </wsdl:input>
      <wsdl:output>
        <soap:body use="literal"/>
      </wsdl:output>
    </wsdl:operation>
    <wsdl:operation name="getAirportInformationByCityOrAirportName">
      <soap:operation soapAction="http://www.webserviceX.NET/getAirportInformationByCityOrAirportName" style="document"/>
      <wsdl:input>
        <soap:body use="literal"/>
      </wsdl:input>
      <wsdl:output>
        <soap:body use="literal"/>
      </wsdl:output>
    </wsdl:operation>
    <wsdl:operation name="GetAirportInformationByCountry">
      <soap:operation soapAction="http://www.webserviceX.NET/GetAirportInformationByCountry" style="document"/>
      <wsdl:input>
        <soap:body use="literal"/>
      </wsdl:input>
      <wsdl:output>
        <soap:body use="literal"/>
      </wsdl:output>
    </wsdl:operation>
    <wsdl:operation name="getAirportInformationByAirportCode">
      <soap:operation soapAction="http://www.webserviceX.NET/getAirportInformationByAirportCode" style="document"/>
      <wsdl:input>
        <soap:body use="literal"/>
      </wsdl:input>
      <wsdl:output>
        <soap:body use="literal"/>
      </wsdl:output>
    </wsdl:operation>
  </wsdl:binding>
  <wsdl:binding name="airportSoap12" type="tns:airportSoap">
    <soap12:binding transport="http://schemas.xmlsoap.org/soap/http"/>
    <wsdl:operation name="getAirportInformationByISOCountryCode">
      <soap12:operation soapAction="http://www.webserviceX.NET/getAirportInformationByISOCountryCode" style="document"/>
      <wsdl:input>
        <soap12:body use="literal"/>
      </wsdl:input>
      <wsdl:output>
        <soap12:body use="literal"/>
      </wsdl:output>
    </wsdl:operation>
    <wsdl:operation name="getAirportInformationByCityOrAirportName">
      <soap12:operation soapAction="http://www.webserviceX.NET/getAirportInformationByCityOrAirportName" style="document"/>
      <wsdl:input>
        <soap12:body use="literal"/>
      </wsdl:input>
      <wsdl:output>
        <soap12:body use="literal"/>
      </wsdl:output>
    </wsdl:operation>
    <wsdl:operation name="GetAirportInformationByCountry">
      <soap12:operation soapAction="http://www.webserviceX.NET/GetAirportInformationByCountry" style="document"/>
      <wsdl:input>
        <soap12:body use="literal"/>
      </wsdl:input>
      <wsdl:output>
        <soap12:body use="literal"/>
      </wsdl:output>
    </wsdl:operation>
    <wsdl:operation name="getAirportInformationByAirportCode">
      <soap12:operation soapAction="http://www.webserviceX.NET/getAirportInformationByAirportCode" style="document"/>
      <wsdl:input>
        <soap12:body use="literal"/>
      </wsdl:input>
      <wsdl:output>
        <soap12:body use="literal"/>
      </wsdl:output>
    </wsdl:operation>
  </wsdl:binding>
  <wsdl:binding name="airportHttpGet" type="tns:airportHttpGet">
    <http:binding verb="GET"/>
    <wsdl:operation name="getAirportInformationByISOCountryCode">
      <http:operation location="/getAirportInformationByISOCountryCode"/>
      <wsdl:input>
        <http:urlEncoded/>
      </wsdl:input>
      <wsdl:output>
        <mime:mimeXml part="Body"/>
      </wsdl:output>
    </wsdl:operation>
    <wsdl:operation name="getAirportInformationByCityOrAirportName">
      <http:operation location="/getAirportInformationByCityOrAirportName"/>
      <wsdl:input>
        <http:urlEncoded/>
      </wsdl:input>
      <wsdl:output>
        <mime:mimeXml part="Body"/>
      </wsdl:output>
    </wsdl:operation>
    <wsdl:operation name="GetAirportInformationByCountry">
      <http:operation location="/GetAirportInformationByCountry"/>
      <wsdl:input>
        <http:urlEncoded/>
      </wsdl:input>
      <wsdl:output>
        <mime:mimeXml part="Body"/>
      </wsdl:output>
    </wsdl:operation>
    <wsdl:operation name="getAirportInformationByAirportCode">
      <http:operation location="/getAirportInformationByAirportCode"/>
      <wsdl:input>
        <http:urlEncoded/>
      </wsdl:input>
      <wsdl:output>
        <mime:mimeXml part="Body"/>
      </wsdl:output>
    </wsdl:operation>
  </wsdl:binding>
  <wsdl:binding name="airportHttpPost" type="tns:airportHttpPost">
    <http:binding verb="POST"/>
    <wsdl:operation name="getAirportInformationByISOCountryCode">
      <http:operation location="/getAirportInformationByISOCountryCode"/>
      <wsdl:input>
        <mime:content type="application/x-www-form-urlencoded"/>
      </wsdl:input>
      <wsdl:output>
        <mime:mimeXml part="Body"/>
      </wsdl:output>
    </wsdl:operation>
    <wsdl:operation name="getAirportInformationByCityOrAirportName">
      <http:operation location="/getAirportInformationByCityOrAirportName"/>
      <wsdl:input>
        <mime:content type="application/x-www-form-urlencoded"/>
      </wsdl:input>
      <wsdl:output>
        <mime:mimeXml part="Body"/>
      </wsdl:output>
    </wsdl:operation>
    <wsdl:operation name="GetAirportInformationByCountry">
      <http:operation location="/GetAirportInformationByCountry"/>
      <wsdl:input>
        <mime:content type="application/x-www-form-urlencoded"/>
      </wsdl:input>
      <wsdl:output>
        <mime:mimeXml part="Body"/>
      </wsdl:output>
    </wsdl:operation>
    <wsdl:operation name="getAirportInformationByAirportCode">
      <http:operation location="/getAirportInformationByAirportCode"/>
      <wsdl:input>
        <mime:content type="application/x-www-form-urlencoded"/>
      </wsdl:input>
      <wsdl:output>
        <mime:mimeXml part="Body"/>
      </wsdl:output>
    </wsdl:operation>
  </wsdl:binding>
  <wsdl:service name="airport">
    <wsdl:port name="airportSoap" binding="tns:airportSoap">
      <soap:address location="http://www.webservicex.net/airport.asmx"/>
    </wsdl:port>
    <wsdl:port name="airportSoap12" binding="tns:airportSoap12">
      <soap12:address location="http://www.webservicex.net/airport.asmx"/>
    </wsdl:port>
    <wsdl:port name="airportHttpGet" binding="tns:airportHttpGet">
      <http:address location="http://www.webservicex.net/airport.asmx"/>
    </wsdl:port>
    <wsdl:port name="airportHttpPost" binding="tns:airportHttpPost">
      <http:address location="http://www.webservicex.net/airport.asmx"/>
    </wsdl:port>
  </wsdl:service>
</wsdl:definitions>]]></con:content><con:type>http://schemas.xmlsoap.org/wsdl/</con:type></con:part></con:definitionCache><con:endpoints><con:endpoint>http://www.webservicex.net/airport.asmx</con:endpoint></con:endpoints><con:operation id="306cead6-608b-4778-9f4a-fa3dc81c0db3" isOneWay="false" action="http://www.webserviceX.NET/getAirportInformationByAirportCode" name="getAirportInformationByAirportCode" bindingOperationName="getAirportInformationByAirportCode" type="Request-Response" inputName="" receivesAttachments="false" sendsAttachments="false" anonymous="optional"><con:settings/><con:call id="6cc52328-c49e-4640-9746-6015607119d0" name="Request 1"><con:settings/><con:encoding>UTF-8</con:encoding><con:endpoint>http://www.webservicex.net/airport.asmx</con:endpoint><con:request><![CDATA[<soapenv:Envelope xmlns:soapenv="http://schemas.xmlsoap.org/soap/envelope/" xmlns:web="http://www.webserviceX.NET">\r
   <soapenv:Header/>\r
   <soapenv:Body>\r
      <web:getAirportInformationByAirportCode>\r
         <!--Optional:-->\r
         <web:airportCode>?</web:airportCode>\r
      </web:getAirportInformationByAirportCode>\r
   </soapenv:Body>\r
</soapenv:Envelope>]]></con:request><con:credentials><con:authType>No Authorization</con:authType></con:credentials><con:jmsConfig JMSDeliveryMode="PERSISTENT"/><con:jmsPropertyConfig/><con:wsaConfig mustUnderstand="NONE" version="200508" action="http://www.webserviceX.NET/getAirportInformationByAirportCode"/><con:wsrmConfig version="1.2"/></con:call></con:operation><con:operation id="b3931836-ce28-449a-96ff-ea8ddbee6ed9" isOneWay="false" action="http://www.webserviceX.NET/getAirportInformationByCityOrAirportName" name="getAirportInformationByCityOrAirportName" bindingOperationName="getAirportInformationByCityOrAirportName" type="Request-Response" inputName="" receivesAttachments="false" sendsAttachments="false" anonymous="optional"><con:settings/><con:call id="5f8500ad-8d1c-44d7-b963-a1c321bde556" name="Request 1"><con:settings><con:setting id="com.eviware.soapui.impl.wsdl.WsdlRequest@request-headers">&lt;xml-fragment/></con:setting></con:settings><con:encoding>UTF-8</con:encoding><con:endpoint>http://www.webservicex.net/airport.asmx</con:endpoint><con:request><![CDATA[<soapenv:Envelope xmlns:soapenv="http://schemas.xmlsoap.org/soap/envelope/" xmlns:web="http://www.webserviceX.NET">\r
   <soapenv:Header/>\r
   <soapenv:Body>\r
      <web:getAirportInformationByCityOrAirportName>\r
         <!--Optional:-->\r
         <web:cityOrAirportName>?</web:cityOrAirportName>\r
      </web:getAirportInformationByCityOrAirportName>\r
   </soapenv:Body>\r
</soapenv:Envelope>]]></con:request><con:credentials><con:authType>No Authorization</con:authType></con:credentials><con:jmsConfig JMSDeliveryMode="PERSISTENT"/><con:jmsPropertyConfig/><con:wsaConfig mustUnderstand="NONE" version="200508" action="http://www.webserviceX.NET/getAirportInformationByCityOrAirportName"/><con:wsrmConfig version="1.2"/></con:call></con:operation><con:operation id="76fd1d77-ef51-45be-90bf-99d9df3aabca" isOneWay="false" action="http://www.webserviceX.NET/GetAirportInformationByCountry" name="GetAirportInformationByCountry" bindingOperationName="GetAirportInformationByCountry" type="Request-Response" inputName="" receivesAttachments="false" sendsAttachments="false" anonymous="optional"><con:settings/><con:call id="955e32e7-f44f-43a8-9ca7-dbdb11ed43ae" name="Request 1"><con:settings/><con:encoding>UTF-8</con:encoding><con:endpoint>http://www.webservicex.net/airport.asmx</con:endpoint><con:request><![CDATA[<soapenv:Envelope xmlns:soapenv="http://schemas.xmlsoap.org/soap/envelope/" xmlns:web="http://www.webserviceX.NET">\r
   <soapenv:Header/>\r
   <soapenv:Body>\r
      <web:GetAirportInformationByCountry>\r
         <!--Optional:-->\r
         <web:country>?</web:country>\r
      </web:GetAirportInformationByCountry>\r
   </soapenv:Body>\r
</soapenv:Envelope>]]></con:request><con:credentials><con:authType>No Authorization</con:authType></con:credentials><con:jmsConfig JMSDeliveryMode="PERSISTENT"/><con:jmsPropertyConfig/><con:wsaConfig mustUnderstand="NONE" version="200508" action="http://www.webserviceX.NET/GetAirportInformationByCountry"/><con:wsrmConfig version="1.2"/></con:call></con:operation><con:operation id="0cbd1ef5-0017-45cd-ba82-cc759bee561f" isOneWay="false" action="http://www.webserviceX.NET/getAirportInformationByISOCountryCode" name="getAirportInformationByISOCountryCode" bindingOperationName="getAirportInformationByISOCountryCode" type="Request-Response" inputName="" receivesAttachments="false" sendsAttachments="false" anonymous="optional"><con:settings/><con:call id="f547993f-8d57-46fe-a8c8-cbc9ce0c4e5b" name="Request 1"><con:settings/><con:encoding>UTF-8</con:encoding><con:endpoint>http://www.webservicex.net/airport.asmx</con:endpoint><con:request><![CDATA[<soapenv:Envelope xmlns:soapenv="http://schemas.xmlsoap.org/soap/envelope/" xmlns:web="http://www.webserviceX.NET">\r
   <soapenv:Header/>\r
   <soapenv:Body>\r
      <web:getAirportInformationByISOCountryCode>\r
         <!--Optional:-->\r
         <web:CountryAbbrviation>?</web:CountryAbbrviation>\r
      </web:getAirportInformationByISOCountryCode>\r
   </soapenv:Body>\r
</soapenv:Envelope>]]></con:request><con:credentials><con:authType>No Authorization</con:authType></con:credentials><con:jmsConfig JMSDeliveryMode="PERSISTENT"/><con:jmsPropertyConfig/><con:wsaConfig mustUnderstand="NONE" version="200508" action="http://www.webserviceX.NET/getAirportInformationByISOCountryCode"/><con:wsrmConfig version="1.2"/></con:call></con:operation></con:interface><con:testSuite id="d8e6af6b-79aa-4c35-8d4e-122857d0d178" name="AirportTestSuite"><con:settings/><con:runType>SEQUENTIAL</con:runType><con:testCase id="d6366c9e-3291-465e-b9aa-bd8871f743dc" failOnError="true" failTestCaseOnErrors="true" keepSession="false" maxResults="0" name="Airport TestCase" searchProperties="true"><con:settings/><con:testStep type="request" name="getAirportInformationByAirportCode" id="76895dcb-cba1-45e6-a4a7-07e0a8ad9cd0"><con:settings/><con:config xsi:type="con:RequestStep" xmlns:xsi="http://www.w3.org/2001/XMLSchema-instance"><con:interface>airportSoap</con:interface><con:operation>getAirportInformationByAirportCode</con:operation><con:request name="getAirportInformationByAirportCode" id="831f519d-cb1d-4f08-a9e0-313c769f0e9d"><con:settings><con:setting id="com.eviware.soapui.impl.wsdl.WsdlRequest@request-headers">&lt;xml-fragment/></con:setting></con:settings><con:encoding>UTF-8</con:encoding><con:endpoint>http://www.webservicex.net/airport.asmx</con:endpoint><con:request><![CDATA[<soapenv:Envelope xmlns:soapenv="http://schemas.xmlsoap.org/soap/envelope/" xmlns:web="http://www.webserviceX.NET">
   <soapenv:Header/>
   <soapenv:Body>
      <web:getAirportInformationByAirportCode>
         <!--Optional:-->
         <web:airportCode>ARN</web:airportCode>
      </web:getAirportInformationByAirportCode>
   </soapenv:Body>
</soapenv:Envelope>]]></con:request><con:assertion type="SOAP Response" id="8f708fef-104d-48c2-be17-25e23d52e36c"/><con:assertion type="Simple Contains" id="af40d4f5-8705-4702-b742-386f41217bfc" name="Contains"><con:configuration><token>ARN</token><ignoreCase>true</ignoreCase><useRegEx>false</useRegEx></con:configuration></con:assertion><con:assertion type="Valid HTTP Status Codes" id="9f5f8885-62f9-4b5c-a82d-e3c68e0dd89b" name="Valid HTTP Status Codes"><con:configuration><codes>200</codes></con:configuration></con:assertion><con:credentials><con:authType>No Authorization</con:authType></con:credentials><con:jmsConfig JMSDeliveryMode="PERSISTENT"/><con:jmsPropertyConfig/><con:wsaConfig mustUnderstand="NONE" version="200508"/><con:wsrmConfig version="1.2"/></con:request></con:config></con:testStep><con:testStep type="properties" name="AirportName" id="fc42f2b9-7d7c-4061-9e96-51706dd51d54"><con:settings/><con:config xsi:type="con:PropertiesStep" saveFirst="true" xmlns:xsi="http://www.w3.org/2001/XMLSchema-instance"><con:properties><con:property><con:name>airportName</con:name><con:value>Stockholm Arlanda</con:value></con:property><con:property><con:name>ariporttwo</con:name><con:value>Add</con:value></con:property></con:properties></con:config></con:testStep><con:testStep type="request" name="getAirportInformationByCityOrAirportName" id="a85290d9-a928-4345-881a-a4753cb339c3"><con:settings/><con:config xsi:type="con:RequestStep" xmlns:xsi="http://www.w3.org/2001/XMLSchema-instance"><con:interface>airportSoap</con:interface><con:operation>getAirportInformationByCityOrAirportName</con:operation><con:request name="getAirportInformationByCityOrAirportName" id="9484e12f-c678-40f9-9794-7628ee50b900"><con:settings><con:setting id="com.eviware.soapui.impl.wsdl.WsdlRequest@request-headers">&lt;xml-fragment/></con:setting></con:settings><con:encoding>UTF-8</con:encoding><con:endpoint>http://www.webservicex.net/airport.asmx</con:endpoint><con:request><![CDATA[<soapenv:Envelope xmlns:soapenv="http://schemas.xmlsoap.org/soap/envelope/" xmlns:web="http://www.webserviceX.NET">
   <soapenv:Header/>
   <soapenv:Body>
      <web:getAirportInformationByCityOrAirportName>
         <!--Optional:-->
         <web:cityOrAirportName>${AirportName#airportName}</web:cityOrAirportName>
      </web:getAirportInformationByCityOrAirportName>
   </soapenv:Body>
</soapenv:Envelope>]]></con:request><con:assertion type="SOAP Response" id="7f5e5b8d-fcfb-480d-a54f-8121f128c25b"/><con:assertion type="Schema Compliance" id="f3190b01-24f2-4246-9851-91786be8a03a"><con:configuration/></con:assertion><con:assertion type="Simple Contains" id="dfb271bd-f9fe-458a-a5c6-5f43750b9b45" name="Contains_Country"><con:configuration><token>Stockholm Arlanda</token><ignoreCase>true</ignoreCase><useRegEx>false</useRegEx></con:configuration></con:assertion><con:assertion type="Valid HTTP Status Codes" id="0ef7635c-80e9-4ca8-a643-814385c6152a" name="Valid HTTP Status Codes"><con:configuration><codes>200</codes></con:configuration></con:assertion><con:credentials><con:authType>No Authorization</con:authType></con:credentials><con:jmsConfig JMSDeliveryMode="PERSISTENT"/><con:jmsPropertyConfig/><con:wsaConfig mustUnderstand="NONE" version="200508"/><con:wsrmConfig version="1.2"/></con:request></con:config></con:testStep><con:testStep type="groovy" name="CountryName_ProjectLevel" id="4fc8f601-c750-4320-a58e-38ea544a976d"><con:settings/><con:config><script>def countryName="Sweden"
log.info(countryName)
//log.info("CountryName:"+""+countryName)
testRunner.testCase.testSuite.project.setPropertyValue("CountryName",countryName)
</script></con:config></con:testStep><con:testStep type="groovy" name="CountryName_GlobalLevel" id="bbf56751-c5bf-4596-9ce6-4f8322d84966"><con:settings/><con:config><script>def countryName="Sweden"
log.info("CountryName:"+""+countryName)
com.eviware.soapui.SoapUI.globalProperties.setPropertyValue("CountryName",countryName)
</script></con:config></con:testStep><con:testStep type="request" name="GetAirportInformationByCountry_ProjectLevel" id="d838267f-4a3a-4140-859f-afbb6e532b01"><con:settings/><con:config xsi:type="con:RequestStep" xmlns:xsi="http://www.w3.org/2001/XMLSchema-instance"><con:interface>airportSoap</con:interface><con:operation>GetAirportInformationByCountry</con:operation><con:request name="GetAirportInformationByCountry_ProjectLevel" id="f57a14e5-bdce-4850-b30d-9e2df12fc7d9"><con:settings><con:setting id="com.eviware.soapui.impl.wsdl.WsdlRequest@request-headers">&lt;xml-fragment/></con:setting></con:settings><con:encoding>UTF-8</con:encoding><con:endpoint>http://www.webservicex.net/airport.asmx</con:endpoint><con:request><![CDATA[<soapenv:Envelope xmlns:soapenv="http://schemas.xmlsoap.org/soap/envelope/" xmlns:web="http://www.webserviceX.NET">
   <soapenv:Header/>
   <soapenv:Body>
      <web:GetAirportInformationByCountry>
         <!--Optional:-->
         <web:country>${#Project#CountryName}</web:country>
      </web:GetAirportInformationByCountry>
   </soapenv:Body>
</soapenv:Envelope>]]></con:request><con:assertion type="SOAP Response" id="11cd6ebe-8c1c-4f71-bed8-0840ee487f7b"/><con:assertion type="Schema Compliance" id="df1ea1ec-663f-4aeb-b7bf-7ab61668519c"><con:configuration/></con:assertion><con:assertion type="Simple Contains" id="188fdec1-0447-4999-966c-c265aecdb624" name="Contains"><con:configuration><token>Sweden</token><ignoreCase>true</ignoreCase><useRegEx>false</useRegEx></con:configuration></con:assertion><con:assertion type="Valid HTTP Status Codes" id="14f3ff04-f1ed-45fa-ae39-3739636af81f" name="Valid HTTP Status Codes"><con:configuration><codes>200
</codes></con:configuration></con:assertion><con:credentials><con:authType>No Authorization</con:authType></con:credentials><con:jmsConfig JMSDeliveryMode="PERSISTENT"/><con:jmsPropertyConfig/><con:wsaConfig mustUnderstand="NONE" version="200508"/><con:wsrmConfig version="1.2"/></con:request></con:config></con:testStep><con:testStep type="request" name="GetAirportInformationByCountry_GloalLevel" id="cb712193-42a3-44b1-b11d-e01fc2aef363"><con:settings/><con:config xsi:type="con:RequestStep" xmlns:xsi="http://www.w3.org/2001/XMLSchema-instance"><con:interface>airportSoap</con:interface><con:operation>GetAirportInformationByCountry</con:operation><con:request name="GetAirportInformationByCountry_GloalLevel" id="f57a14e5-bdce-4850-b30d-9e2df12fc7d9"><con:settings><con:setting id="com.eviware.soapui.impl.wsdl.WsdlRequest@request-headers">&lt;xml-fragment/></con:setting></con:settings><con:encoding>UTF-8</con:encoding><con:endpoint>http://www.webservicex.net/airport.asmx</con:endpoint><con:request><![CDATA[<soapenv:Envelope xmlns:soapenv="http://schemas.xmlsoap.org/soap/envelope/" xmlns:web="http://www.webserviceX.NET">
   <soapenv:Header/>
   <soapenv:Body>
      <web:GetAirportInformationByCountry>
         <!--Optional:-->
         <web:country>${CountryName}</web:country>
      </web:GetAirportInformationByCountry>
   </soapenv:Body>
</soapenv:Envelope>]]></con:request><con:assertion type="SOAP Response" id="11cd6ebe-8c1c-4f71-bed8-0840ee487f7b"/><con:assertion type="Schema Compliance" id="df1ea1ec-663f-4aeb-b7bf-7ab61668519c"><con:configuration/></con:assertion><con:assertion type="Simple Contains" id="188fdec1-0447-4999-966c-c265aecdb624" name="Contains"><con:configuration><token>Sweden</token><ignoreCase>true</ignoreCase><useRegEx>false</useRegEx></con:configuration></con:assertion><con:assertion type="Valid HTTP Status Codes" id="14f3ff04-f1ed-45fa-ae39-3739636af81f" name="Valid HTTP Status Codes"><con:configuration><codes>200
</codes></con:configuration></con:assertion><con:credentials><con:authType>No Authorization</con:authType></con:credentials><con:jmsConfig JMSDeliveryMode="PERSISTENT"/><con:jmsPropertyConfig/><con:wsaConfig mustUnderstand="NONE" version="200508"/><con:wsrmConfig version="1.2"/></con:request></con:config></con:testStep><con:testStep type="request" name="getAirportInformationByISOCountryCode_ProjectLevel" id="024deef3-e3d2-45f1-a61c-21606a038d93"><con:settings/><con:config xsi:type="con:RequestStep" xmlns:xsi="http://www.w3.org/2001/XMLSchema-instance"><con:interface>airportSoap</con:interface><con:operation>getAirportInformationByISOCountryCode</con:operation><con:request name="getAirportInformationByISOCountryCode_ProjectLevel" id="a2415520-a5aa-46a0-a855-22ca8bcedfad"><con:settings><con:setting id="com.eviware.soapui.impl.wsdl.WsdlRequest@request-headers">&lt;xml-fragment/></con:setting></con:settings><con:encoding>UTF-8</con:encoding><con:endpoint>http://www.webservicex.net/airport.asmx</con:endpoint><con:request><![CDATA[<soapenv:Envelope xmlns:soapenv="http://schemas.xmlsoap.org/soap/envelope/" xmlns:web="http://www.webserviceX.NET">
   <soapenv:Header/>
   <soapenv:Body>
      <web:getAirportInformationByISOCountryCode>
         <!--Optional:-->
         <web:CountryAbbrviation>${#Project#CountryAbbrivation}</web:CountryAbbrviation>
      </web:getAirportInformationByISOCountryCode>
   </soapenv:Body>
</soapenv:Envelope>]]></con:request><con:assertion type="SOAP Response" id="7d31a719-b318-4334-8594-cd22eec74c2c"/><con:assertion type="Schema Compliance" id="cc0bc1ec-eef2-4890-9d83-2144f41d1313"><con:configuration/></con:assertion><con:assertion type="Simple Contains" id="7040e87a-bd67-49a9-9a2b-50d424896cae" name="Contains"><con:configuration><token>Se</token><ignoreCase>true</ignoreCase><useRegEx>false</useRegEx></con:configuration></con:assertion><con:assertion type="Valid HTTP Status Codes" id="f9a2fc04-2e92-404a-8dc5-7c765787c0ee" name="Valid HTTP Status Codes"><con:configuration><codes>200</codes></con:configuration></con:assertion><con:credentials><con:authType>No Authorization</con:authType></con:credentials><con:jmsConfig JMSDeliveryMode="PERSISTENT"/><con:jmsPropertyConfig/><con:wsaConfig mustUnderstand="NONE" version="200508"/><con:wsrmConfig version="1.2"/></con:request></con:config></con:testStep><con:testStep type="groovy" name="CountryAbbrevation_ProjectLevel" id="1e87ae70-6f08-4c40-97c3-d134e3fc2b68"><con:settings/><con:config><script>import groovy.util.XmlSlurper
def responseContent=testRunner.testCase.getTestStepByName("getAirportInformationByCityOrAirportName").getPropertyValue("response")
log.info(responseContent)

def xmlResponse=new XmlSlurper().parseText(responseContent)
log.info(xmlResponse)
def slurperResponse=new XmlSlurper().parseText(xmlResponse.Body.getAirportInformationByCityOrAirportNameResponse.getAirportInformationByCityOrAirportNameResult.toString())
log.info(slurperResponse)
def countryAbbrviation=slurperResponse.Table.CountryAbbrviation[0]

testRunner.testCase.testSuite.project.setPropertyValue("CountryAbbrivation",countryAbbrviation.toString())
</script></con:config></con:testStep><con:testStep type="groovy" name="CountryAbbrevation_GlobalLevel" id="64ba60b9-918f-493b-a831-cede02d0a878" disabled="true"><con:settings/><con:config><script>/*

def countryCode="SE"
log.info("CountryCode:"+""+countryCode)
com.eviware.soapui.SoapUI.globalProperties.setPropertyValue("CountryCode",countryCode)
*/</script></con:config></con:testStep><con:properties/></con:testCase><con:properties/></con:testSuite><con:properties><con:property><con:name>CountryName</con:name><con:value>Sweden</con:value></con:property><con:property><con:name>CountryAbbrivation</con:name><con:value>SE</con:value></con:property><con:property><con:name>et</con:name><con:value>et</con:value></con:property></con:properties><con:wssContainer/><con:oAuth2ProfileContainer/><con:oAuth1ProfileContainer/><con:sensitiveInformation/></con:soapui-project>